nullspace-0.0.56.dist-info/LICENSE
nullspace-0.0.56.dist-info/WHEEL
nullspace-0.0.56.dist-info/METADATA
nullspace-0.0.56.dist-info/top_level.txt
nullspace-0.0.56.dist-info/RECORD
nullspace-0.0.56.dist-info/AUTHORS.rst
nullspace/se3.py
nullspace/__init__.py
nullspace/quadrupedsym.py
nullspace/rbda.py
nullspace/svd_wrapper.cpython-312-x86_64-linux-gnu.so
nullspace/_version.py
nullspace/python/eg.pxd
nullspace/python/eigen.pxd
nullspace/python/svd_wrapper.cpp
nullspace/python/svd_wrapper.pyx
nullspace/python/csvd.pxd
nullspace/tests/__init__.py
nullspace/tests/test_examples.py
nullspace/tests/conftest.py
nullspace/tests/test_xyz.py
nullspace/models/__init__.py
nullspace/models/structure.py
nullspace/models/quadruped.py
nullspace/models/hand.py
