Metadata-Version: 2.2
Name: nullspace
Version: 0.0.56
Summary: Python package for doing science.
Home-page: https://github.com/ke-zhang-rd/nullspace
Author: G
Author-email: abc@outlook.com
License: BSD (3-clause)
Classifier: Development Status :: 2 - Pre-Alpha
Classifier: Natural Language :: English
Classifier: Programming Language :: Python :: 3
Requires-Python: >=3.6
License-File: LICENSE
License-File: AUTHORS.rst
Requires-Dist: cibuildwheel
Requires-Dist: cookiecutter
Requires-Dist: cython
Requires-Dist: ipython
Requires-Dist: matplotlib
Requires-Dist: numpy
Requires-Dist: numpydoc
Requires-Dist: nbsphinx
Requires-Dist: pexpect
Requires-Dist: pytest
Requires-Dist: sphinx<=8.1.3
Requires-Dist: sphinx-copybutton
Requires-Dist: sphinx_rtd_theme
Requires-Dist: sympy
Dynamic: author
Dynamic: author-email
Dynamic: classifier
Dynamic: description
Dynamic: home-page
Dynamic: license
Dynamic: requires-dist
Dynamic: requires-python
Dynamic: summary
